netbox_grass/__init__.py
netbox_grass-0.1.1.dist-info/METADATA
netbox_grass-0.1.1.dist-info/WHEEL
netbox_grass-0.1.1.dist-info/top_level.txt
netbox_grass-0.1.1.dist-info/RECORD
